setup.py
pushy_utils/__init__.py
pushy_utils/file.py
pushy_utils/network.py
pushy_utils/timeutil.py
pushy_utils/txt.py
pushy_utils.egg-info/PKG-INFO
pushy_utils.egg-info/SOURCES.txt
pushy_utils.egg-info/dependency_links.txt
pushy_utils.egg-info/requires.txt
pushy_utils.egg-info/top_level.txt