Metadata-Version: 1.0
Name: pushy-utils
Version: 0.0.1
Summary: Pushy dev utils
Home-page: https://github.com/pushyzheng
Author: Pushy
Author-email: 1437876073@qq.com
License: UNKNOWN
Platform: UNKNOWN
